{
	"recaptcha": {
		"secretkey": "6LcO1EUUAAAAAHWS9Pdvj5SHCjkbNfStLPq8oVoT"
	},
	"plivo": {
		"authtoken": "ZjkzYjMfeOWJiYzUxZGRdsOTY4NDcyNmQwOTUy",
		"authid": "MAMGM1YJMLDD0MDC4MG"
	},
	"algolia": {
		"search_key": "c283440030db1f9446e8b410f7352479",
		"app_id": "TOS20M7VT1",
		"api_key": "c76095f595b5add42fa0f85c0fcfd45e"
	},
	"setting": {
		"feedemail": "marko.b.stanicic@gmail.com",
		"appname": "React Social Network"
	},
	"gmail": {
		"email": "marko.b.stanicic@gmail.com",
		"password": "br0d0gradnja"
	},
	"phone": {
		"sourcenumber": ""
	}
}
